anyid/__init__.py
anyid/crypto_random/__init__.py
anyid/crypto_random/generator.py
anyid/cuid/__init__.py
anyid/cuid/generator.py
anyid/cuid2/__init__.py
anyid/cuid2/generator.py
anyid/cuid2/utils.py
anyid/haikunator/__init__.py
anyid/haikunator/data.py
anyid/haikunator/generator.py
anyid/ksuid/__init__.py
anyid/ksuid/generator.py
anyid/nanoid/__init__.py
anyid/nanoid/generator.py
anyid/petname/__init__.py
anyid/petname/data.py
anyid/petname/generator.py
anyid/snowflake/__init__.py
anyid/snowflake/generator.py
anyid/ulid/__init__.py
anyid/ulid/generator.py
anyid/uuid/__init__.py
anyid/uuid/generator.py
anyid/xid/__init__.py
anyid/xid/generator.py
anyid-0.5.0.dist-info/METADATA
anyid-0.5.0.dist-info/WHEEL
anyid-0.5.0.dist-info/top_level.txt
anyid-0.5.0.dist-info/RECORD
