Metadata-Version: 2.4
Name: anyid
Version: 0.5.0
Summary: A unified Python ID generator library.
Author-email: Adel Rahimi <rahimi.adel@gmail.com>
Project-URL: Homepage, https://github.com/adelra/anyid
Project-URL: Bug Tracker, https://github.com/adelra/anyid/issues
Classifier: Programming Language :: Python :: 3
Classifier: License :: OSI Approved :: MIT License
Classifier: Operating System :: OS Independent
Requires-Python: >=3.8
Provides-Extra: dev
Requires-Dist: pytest; extra == "dev"
Requires-Dist: pytest-cov; extra == "dev"
Requires-Dist: ruff; extra == "dev"
Requires-Dist: mypy; extra == "dev"
Requires-Dist: black; extra == "dev"
Requires-Dist: hypothesis; extra == "dev"
